README.rst
setup.py
tornado_websocket_server/__init__.py
tornado_websocket_server/authorization.py
tornado_websocket_server/helpers.py
tornado_websocket_server/server.py
tornado_websocket_server/settings.py
tornado_websocket_server/tests.py
tornado_websocket_server.egg-info/PKG-INFO
tornado_websocket_server.egg-info/SOURCES.txt
tornado_websocket_server.egg-info/dependency_links.txt
tornado_websocket_server.egg-info/requires.txt
tornado_websocket_server.egg-info/top_level.txt