Metadata-Version: 1.1
Name: tornado-websocket-server
Version: 0.1.0a1
Summary: WebSocket server created with Tornado framework.
Home-page: https://github.com/kacperd/dk-tornado-websocket
Author: Kacper Dziubek
Author-email: kacperd@vp.pl
License: MIT
Keywords: websockets tornado redis asynchronous
Platform: UNKNOWN
Classifier: Development Status :: 3 - Alpha
Classifier: Intended Audience :: Developers
Classifier: Topic :: Software Development :: Build Tools
Classifier: License :: OSI Approved :: MIT License
Classifier: Programming Language :: Python :: 2.7
Classifier: Programming Language :: Python :: 3.5
